pdf_mcp/__init__.py
pdf_mcp/cache.py
pdf_mcp/extractor.py
pdf_mcp/server.py
pdf_mcp/url_fetcher.py
pdf_mcp-1.1.1.dist-info/METADATA
pdf_mcp-1.1.1.dist-info/WHEEL
pdf_mcp-1.1.1.dist-info/entry_points.txt
pdf_mcp-1.1.1.dist-info/licenses/LICENSE
pdf_mcp-1.1.1.dist-info/RECORD
