Metadata-Version: 2.4
Name: pdf-mcp
Version: 1.1.1
Summary: Production-ready MCP server for PDF processing with intelligent caching. Extract text, search, and analyze PDFs with AI agents.
Project-URL: Homepage, https://github.com/jztan/pdf-mcp
Project-URL: Documentation, https://github.com/jztan/pdf-mcp#readme
Project-URL: Repository, https://github.com/jztan/pdf-mcp
Project-URL: Issues, https://github.com/jztan/pdf-mcp/issues
Project-URL: Changelog, https://github.com/jztan/pdf-mcp/blob/master/CHANGELOG.md
Author-email: Kevin Tan <jingzheng.tan@gmail.com>
Maintainer-email: Kevin Tan <jingzheng.tan@gmail.com>
License: MIT
License-File: LICENSE
Keywords: ai,ai-agent,anthropic,claude,document-ai,document-processing,llm,mcp,model-context-protocol,pdf,pdf-extraction,pdf-reader
Classifier: Development Status :: 4 - Beta
Classifier: Intended Audience :: Developers
Classifier: License :: OSI Approved :: MIT License
Classifier: Operating System :: OS Independent
Classifier: Programming Language :: Python :: 3
Classifier: Programming Language :: Python :: 3.10
Classifier: Programming Language :: Python :: 3.11
Classifier: Programming Language :: Python :: 3.12
Classifier: Topic :: Scientific/Engineering :: Artificial Intelligence
Classifier: Topic :: Software Development :: Libraries :: Python Modules
Classifier: Topic :: Text Processing :: General
Requires-Python: >=3.10
Requires-Dist: httpx>=0.27.0
Requires-Dist: mcp>=1.2.0
Requires-Dist: pydantic>=2.0
Requires-Dist: pymupdf>=1.24.0
Provides-Extra: dev
Requires-Dist: mypy>=1.8.0; extra == 'dev'
Requires-Dist: pillow>=10.0; extra == 'dev'
Requires-Dist: pytest-asyncio>=0.23.0; extra == 'dev'
Requires-Dist: pytest-cov>=4.0; extra == 'dev'
Requires-Dist: pytest>=8.0; extra == 'dev'
Requires-Dist: ruff>=0.2.0; extra == 'dev'
